MANIFEST.in
README.rst
setup.py
src/turbo_disco/__about__.py
src/turbo_disco/__init__.py
src/turbo_disco/foo.py
src/turbo_disco.egg-info/PKG-INFO
src/turbo_disco.egg-info/SOURCES.txt
src/turbo_disco.egg-info/dependency_links.txt
src/turbo_disco.egg-info/not-zip-safe
src/turbo_disco.egg-info/requires.txt
src/turbo_disco.egg-info/top_level.txt
tests/test_foo.py